g2p_id/__init__.py
g2p_id/bert.py
g2p_id/g2p.py
g2p_id/lstm.py
g2p_id/onnx_utils.py
g2p_id/text_processor.py
g2p_id/models/bert/bert_mlm.onnx
g2p_id/models/bert/config.json
g2p_id/models/bert/token2id.json
g2p_id/models/lstm/config.json
g2p_id/models/lstm/decoder_model.onnx
g2p_id/models/lstm/encoder_model.onnx
g2p_id/models/lstm/g2id.json
g2p_id/models/lstm/p2id.json
g2p_id/resources/currency.tsv
g2p_id/resources/homographs_id.tsv
g2p_id/resources/id_posp_tagger.pickle
g2p_id/resources/lexicon_id.tsv
g2p_id/resources/measurements.tsv
g2p_id/resources/timezones.tsv
g2p_id_py-0.4.2.dist-info/LICENSE.md
g2p_id_py-0.4.2.dist-info/METADATA
g2p_id_py-0.4.2.dist-info/NOTICE.md
g2p_id_py-0.4.2.dist-info/WHEEL
g2p_id_py-0.4.2.dist-info/top_level.txt
g2p_id_py-0.4.2.dist-info/RECORD
