Metadata-Version: 2.1
Name: g2p_id_py
Version: 0.4.2
Summary: Indonesian G2P.
Home-page: https://github.com/bookbot-kids/g2p_id
Author: w11wo
Author-email: wilson@bookbotkids.com
License: Apache License
Platform: linux
Platform: unix
Platform: windows
Requires-Python: >=3.8
License-File: LICENSE.md
License-File: NOTICE.md
Requires-Dist: num2words
Requires-Dist: nltk==3.9.1
Requires-Dist: onnxruntime
